fairground/__init__.py
fairground/fastapi/__init__.py
fairground/fastapi/app.py
fairground/fastapi/tests/__init__.py
fairground/fastapi/tests/conftest.py
fairground/fastapi/tests/test_app.py
fairground/intersectional.py
fairground/permutations.py
fairground/tests/__init__.py
fairground/tests/baseline_images/test_permutation/plot_family_wise_permutation_analysis.png
fairground/tests/baseline_images/test_utils/disparate_impact_ratio.png
fairground/tests/baseline_images/test_utils/disparate_impact_ratio_multi_combinations.png
fairground/tests/baseline_images/test_utils/job_selection_rate.png
fairground/tests/baseline_images/test_utils/parity_difference.png
fairground/tests/baseline_images/test_utils/parity_difference_more_than_3.png
fairground/tests/baseline_images/test_utils/parity_difference_more_than_3_scatter.png
fairground/tests/baseline_images/test_utils/parity_difference_more_than_3_scatter_multiple.png
fairground/tests/baseline_images/test_utils/selection_rate.png
fairground/tests/baseline_images/test_utils/selection_rate_multiple.png
fairground/tests/conftest.py
fairground/tests/excel2csv_v2.csv
fairground/tests/excel2csv_v2_more_than_3.csv
fairground/tests/excel2csv_v4.csv
fairground/tests/image_comparison.py
fairground/tests/test_permutation.py
fairground/tests/test_typer.py
fairground/tests/test_utils.py
fairground/typer.py
fairground/utils.py
fairground-0.0.0a11.dist-info/METADATA
fairground-0.0.0a11.dist-info/WHEEL
fairground-0.0.0a11.dist-info/RECORD
