Metadata-Version: 2.1
Name: fairground
Version: 0.0.0a11
Summary: Compliance Tools for statistical analysis and debiasing for LLM powered applicant tracking systems.
License: UNLICENSED
Author: n Clara Schumann
Author-email: clara@coefficient.ai
Requires-Python: >=3.12.7,<4.0.0
Classifier: License :: Other/Proprietary License
Classifier: Programming Language :: Python :: 3
Classifier: Programming Language :: Python :: 3.13
Requires-Dist: faker (>=30.1.0,<31.0.0)
Requires-Dist: fastapi (>=0.115.2,<0.116.0)
Requires-Dist: matplotlib (>=3.9.2,<4.0.0)
Requires-Dist: pandas (>=2.2.3,<3.0.0)
Requires-Dist: presidio-structured (>=0.0.2a0,<0.0.3)
Requires-Dist: python-multipart (>=0.0.12,<0.0.13)
Requires-Dist: scipy (>=1.14.1,<2.0.0)
Requires-Dist: seaborn (>=0.13.2,<0.14.0)
Requires-Dist: uvicorn (>=0.31.0,<0.32.0)
